apriori_python/__init__.py
apriori_python/apriori.py
apriori_python/utils.py
apriori_python-1.0.4.dist-info/LICENSE.txt
apriori_python-1.0.4.dist-info/METADATA
apriori_python-1.0.4.dist-info/WHEEL
apriori_python-1.0.4.dist-info/top_level.txt
apriori_python-1.0.4.dist-info/RECORD
