Metadata-Version: 2.1
Name: apriori_python
Version: 1.0.4
Summary: A simple apriori algorithm python implementation
Home-page: https://github.com/chonyy/apriori_python
Author: Chonyy
Author-email: tcheon8788@gmail.com
License: UNKNOWN
Platform: UNKNOWN
Classifier: Programming Language :: Python :: 3
Classifier: License :: OSI Approved :: MIT License
Classifier: Operating System :: OS Independent
Requires-Python: >=3.6
